{
	"TransferFunctionPresets" : 
	{
		"Groups" : "[{\"groupName\":\"Default\",\"presets\":[\"Fast\",\"Turbo\",\"Cool to Warm\",\"Cool to Warm (Extended)\",\"Black-Body Radiation\",\"X Ray\",\"Inferno (matplotlib)\",\"Black, Blue and White\",\"Blue Orange (divergent)\",\"Viridis (matplotlib)\",\"Cold and Hot\",\"Linear Green (Gr4L)\",\"Rainbow Desaturated\",\"Blue - Green - Orange\",\"Rainbow Uniform\",\"Yellow - Gray - Blue\"]},{\"groupName\":\"Diverging\",\"presets\":[\"Cool to Warm (Extended)\",\"Blue Orange (divergent)\",\"Gray and Red\",\"Rainbow Uniform\",\"Cold and Hot\",\"Warm to Cool\",\"Warm to Cool (Extended)\",\"coolwarm\",\"BuRd\",\"Spectral_lowBlow\",\"GnRP\",\"GYPi\",\"GnYlRd\",\"GBBr\",\"PuOr\",\"PRGn\",\"PiYG\",\"OrPu\",\"BrBG\",\"erdc_divHi_purpleGreen\",\"erdc_divHi_purpleGreen_dim\",\"nic_Edge\",\"erdc_iceFire_H\",\"GyRd\",\"Muted Blue-Green\",\"Green-Blue Asymmetric Divergent (62Blbc)\",\"Asymmetrical Earth Tones (6_21b)\",\"erdc_divLow_icePeach\",\"erdc_divLow_purpleGreen\",\"Haze_green\",\"Haze_lime\",\"Haze\",\"Haze_cyan\",\"erdc_iceFire_L\"]},{\"groupName\":\"Isoluminant\",\"presets\":[\"Cool to Warm\",\"Warm to Cool\",\"CIELab Blue to Red\",\"erdc_rainbow_bright\",\"erdc_rainbow_dark\",\"nic_CubicL\",\"nic_CubicYF\",\"erdc_blue2gold\",\"hue_L60\"]},{\"groupName\":\"Linear\",\"presets\":[\"X Ray\",\"Black, Blue and White\",\"Linear Green (Gr4L)\",\"Viridis (matplotlib)\",\"Inferno (matplotlib)\",\"Fast (Reds)\",\"Fast (Blues)\",\"Grayscale\",\"bone_Matlab\",\"gray_Matlab\",\"GnBu\",\"Greens\",\"GREEN-WHITE_LINEAR\",\"Linear Blue (8_31f)\",\"Blues\",\"BuPu\",\"erdc_blue_BW\",\"BLUE-WHITE\",\"erdc_magenta_BW\",\"magenta\",\"erdc_purple_BW\",\"Purples\",\"PuBu\",\"erdc_red_BW\",\"Reds\",\"erdc_green2yellow_BW\",\"erdc_blue2yellow\",\"erdc_blue2gold\",\"Blue to Yellow\",\"blue2yellow\",\"Cividis\",\"CIELab Blue to Red\",\"BuGn\",\"GnBuPu\",\"BuGnYl\",\"Linear YGB 1211g\",\"erdc_blue2green_muted\",\"erdc_cyan2orange\",\"erdc_purple2green\",\"erdc_purple2green_dark\",\"erdc_blue2green_BW\",\"blue2cyan\",\"erdc_blue2cyan_BW\",\"erdc_marine2gold_BW\",\"erdc_blue2gold_BW\",\"erdc_sapphire2gold_BW\",\"erdc_red2purple_BW\",\"erdc_purple2pink_BW\",\"PuRd\",\"RdPu\",\"RED-PURPLE\",\"Yellow 15\",\"RED_TEMPERATURE\",\"Oranges\",\"RdOr\",\"erdc_orange_BW\",\"heated_object\",\"erdc_gold_BW\",\"erdc_brown_BW\",\"copper_Matlab\",\"pink_Matlab\",\"BrOrYl\",\"RdOrYl\",\"Block-Body Radiation\",\"2hot\",\"erdc_red2yellow_BW\",\"Black, Orange, and White\",\"erdc_pbj_lin\",\"Magma (matplotlib)\",\"Plasma (matplotlib)\"]},{\"groupName\":\"Rainbow\",\"presets\":[\"Fast\",\"Rainbow Desaturated\",\"Rainbow Uniform\",\"Turbo\",\"Jet\",\"Blue to Red Rainbow\",\"Rainbow Blended White\",\"Rainbow Blended Grey\",\"Rainbow Blended Black\",\"erdc_rainbow_bright\",\"erdc_rainbow_dark\",\"nic_CubicL\",\"nic_Edge\",\"hsv\"]},{\"groupName\":\"Structured\",\"presets\":[\"Blue - Green - Orange\",\"Rainbow Desaturated\",\"Yellow - Gray - Blue\",\"Rainbow Blended Black\",\"Rainbow Blended Grey\",\"Rainbow Blended White\",\"blot\",\"hsv\",\"KAAMS Step\",\"Spectrum Step\",\"Blues Step\",\"Wildflower Step\",\"Cool Step\",\"Warm Step\",\"Citrus Step\",\"Traffic Lights Step\",\"Traffic Lights For Deuteranopes Step\",\"Traffic Lights For Deuteranopes 2 Step\"]}]"
	},
	"array_lookup_tables" : 
	{
		"T" : 
		{
			"PVLookupTable" : 
			{
				"ColorSpace" : 3,
				"RGBPoints" : 
				[
					323.0,
					0.050382999999999997,
					0.029803,
					0.52797499999999997,
					323.00024512499999,
					0.063535999999999995,
					0.028426,
					0.53312400000000004,
					323.00049018750002,
					0.075353000000000003,
					0.027206000000000001,
					0.53800700000000001,
					323.00073531250001,
					0.086221999999999993,
					0.026124999999999999,
					0.54265799999999997,
					323.00098037499998,
					0.096379000000000006,
					0.025165,
					0.54710300000000001,
					323.00122549999998,
					0.10598,
					0.024309000000000001,
					0.55136799999999997,
					323.0014705625,
					0.115124,
					0.023556000000000001,
					0.55546799999999996,
					323.0017156875,
					0.123903,
					0.022877999999999999,
					0.559423,
					323.00196081249999,
					0.132381,
					0.022258,
					0.56325000000000003,
					323.00220587500002,
					0.14060300000000001,
					0.021687000000000001,
					0.56695899999999999,
					323.00245100000001,
					0.14860699999999999,
					0.021153999999999999,
					0.57056200000000001,
					323.00269606249998,
					0.156421,
					0.020650999999999999,
					0.57406500000000005,
					323.00294118750003,
					0.16406999999999999,
					0.020171000000000001,
					0.57747800000000005,
					323.00318625,
					0.171574,
					0.019706000000000001,
					0.58080600000000004,
					323.00343137499999,
					0.17895,
					0.019251999999999998,
					0.58405399999999996,
					323.00367649999998,
					0.18621299999999999,
					0.018803,
					0.58722799999999997,
					323.00392156250001,
					0.19337399999999999,
					0.018353999999999999,
					0.59033000000000002,
					323.0041666875,
					0.20044500000000001,
					0.017902000000000001,
					0.593364,
					323.00441174999997,
					0.20743500000000001,
					0.017441999999999999,
					0.596333,
					323.00465687500002,
					0.21435000000000001,
					0.016972999999999999,
					0.59923899999999997,
					323.00490193749999,
					0.221197,
					0.016497000000000001,
					0.60208300000000003,
					323.00514706249999,
					0.22798299999999999,
					0.016007,
					0.60486700000000004,
					323.00539218749998,
					0.23471500000000001,
					0.015502,
					0.60759200000000002,
					323.00563725000001,
					0.241396,
					0.014978999999999999,
					0.610259,
					323.005882375,
					0.248032,
					0.014439,
					0.61286799999999997,
					323.00612743750003,
					0.25462699999999999,
					0.013882,
					0.61541900000000005,
					323.00637256250002,
					0.261183,
					0.013308,
					0.61791099999999999,
					323.00661762499999,
					0.26770300000000002,
					0.012716,
					0.62034599999999995,
					323.00686274999998,
					0.27419100000000002,
					0.012109,
					0.622722,
					323.00710781250001,
					0.28064800000000001,
					0.011488,
					0.62503799999999998,
					323.0073529375,
					0.287076,
					0.010855,
					0.62729500000000005,
					323.00759806249999,
					0.29347800000000002,
					0.010213,
					0.62948999999999999,
					323.00784312500002,
					0.29985499999999998,
					0.0095610000000000001,
					0.63162399999999996,
					323.00808825000001,
					0.30620999999999998,
					0.0089020000000000002,
					0.63369399999999998,
					323.00833331249999,
					0.31254300000000002,
					0.0082389999999999998,
					0.63570000000000004,
					323.00857843749998,
					0.31885599999999997,
					0.0075760000000000003,
					0.63763999999999998,
					323.00882350000001,
					0.32514999999999999,
					0.0069150000000000001,
					0.63951199999999997,
					323.009068625,
					0.331426,
					0.0062610000000000001,
					0.641316,
					323.00931374999999,
					0.33768300000000001,
					0.0056179999999999997,
					0.64304899999999998,
					323.00955881250002,
					0.34392499999999998,
					0.0049909999999999998,
					0.64471000000000001,
					323.00980393750001,
					0.35015000000000002,
					0.0043819999999999996,
					0.64629800000000004,
					323.01004899999998,
					0.35635899999999998,
					0.0037980000000000002,
					0.64781,
					323.01029412499997,
					0.36255300000000001,
					0.0032429999999999998,
					0.64924499999999996,
					323.0105391875,
					0.36873299999999998,
					0.0027239999999999999,
					0.65060099999999998,
					323.01078431249999,
					0.37489699999999998,
					0.002245,
					0.65187600000000001,
					323.01102943749999,
					0.38104700000000002,
					0.0018140000000000001,
					0.65306799999999998,
					323.01127450000001,
					0.387183,
					0.0014339999999999999,
					0.65417700000000001,
					323.01151962500001,
					0.39330399999999999,
					0.001114,
					0.65519899999999998,
					323.01176468749998,
					0.39941100000000002,
					0.00085899999999999995,
					0.65613299999999997,
					323.01200981250003,
					0.405503,
					0.000678,
					0.65697700000000003,
					323.012254875,
					0.41158,
					0.00057700000000000004,
					0.65773000000000004,
					323.01249999999999,
					0.41764200000000001,
					0.00056400000000000005,
					0.65839000000000003,
					323.01274512499998,
					0.42368899999999998,
					0.00064599999999999998,
					0.65895599999999999,
					323.01299018750001,
					0.42971900000000002,
					0.00083100000000000003,
					0.65942500000000004,
					323.0132353125,
					0.43573400000000001,
					0.001127,
					0.65979699999999997,
					323.01348037499997,
					0.44173200000000001,
					0.0015399999999999999,
					0.66006900000000002,
					323.01372550000002,
					0.447714,
					0.0020799999999999998,
					0.66024000000000005,
					323.01397056249999,
					0.453677,
					0.0027550000000000001,
					0.66030999999999995,
					323.01421568749998,
					0.459623,
					0.0035739999999999999,
					0.660277,
					323.01446081249998,
					0.46555000000000002,
					0.0045450000000000004,
					0.66013900000000003,
					323.014705875,
					0.47145700000000001,
					0.0056779999999999999,
					0.65989699999999996,
					323.014951,
					0.47734399999999999,
					0.0069800000000000001,
					0.65954900000000005,
					323.01519606250002,
					0.48320999999999997,
					0.0084600000000000005,
					0.65909499999999999,
					323.01544118750002,
					0.48905500000000002,
					0.010127000000000001,
					0.65853399999999995,
					323.01568624999999,
					0.49487700000000001,
					0.011990000000000001,
					0.65786500000000003,
					323.01593137499998,
					0.50067799999999996,
					0.014055,
					0.65708800000000001,
					323.01617649999997,
					0.50645399999999996,
					0.016333,
					0.65620199999999995,
					323.0164215625,
					0.51220600000000005,
					0.018832999999999999,
					0.65520900000000004,
					323.01666668749999,
					0.51793299999999998,
					0.021562999999999999,
					0.65410900000000005,
					323.01691175000002,
					0.52363300000000002,
					0.024532000000000002,
					0.65290099999999995,
					323.01715687500001,
					0.52930600000000005,
					0.027747000000000001,
					0.651586,
					323.01740193749998,
					0.53495199999999998,
					0.031217000000000002,
					0.65016499999999999,
					323.01764706249998,
					0.54056999999999999,
					0.034950000000000002,
					0.64863999999999999,
					323.01789218750002,
					0.546157,
					0.038954000000000003,
					0.64700999999999997,
					323.01813725,
					0.55171499999999996,
					0.043136000000000001,
					0.64527699999999999,
					323.01838237499999,
					0.55724300000000004,
					0.047330999999999998,
					0.64344299999999999,
					323.01862743750002,
					0.56273799999999996,
					0.051545000000000001,
					0.641509,
					323.01887256250001,
					0.56820099999999996,
					0.055778000000000001,
					0.63947699999999996,
					323.01911762499998,
					0.57363200000000003,
					0.060027999999999998,
					0.63734900000000005,
					323.01936275000003,
					0.57902900000000002,
					0.064296000000000006,
					0.63512599999999997,
					323.0196078125,
					0.58439099999999999,
					0.068579000000000001,
					0.63281200000000004,
					323.01985293749999,
					0.58971899999999999,
					0.072877999999999998,
					0.63040799999999997,
					323.02009806249998,
					0.59501099999999996,
					0.077189999999999995,
					0.62791699999999995,
					323.02034312500001,
					0.60026599999999997,
					0.081516000000000005,
					0.62534199999999995,
					323.02058825,
					0.60548500000000005,
					0.085854,
					0.62268599999999996,
					323.02083331249997,
					0.61066699999999996,
					0.090204000000000006,
					0.61995100000000003,
					323.02107843750002,
					0.61581200000000003,
					0.094563999999999995,
					0.61714000000000002,
					323.02132349999999,
					0.620919,
					0.098933999999999994,
					0.61425700000000005,
					323.02156862499999,
					0.62598699999999996,
					0.103312,
					0.61130499999999999,
					323.02181374999998,
					0.63101700000000005,
					0.107699,
					0.60828700000000002,
					323.02205881250001,
					0.63600800000000002,
					0.112092,
					0.60520499999999999,
					323.0223039375,
					0.64095899999999995,
					0.116492,
					0.60206499999999996,
					323.02254900000003,
					0.645872,
					0.12089800000000001,
					0.59886700000000004,
					323.02279412500002,
					0.65074600000000005,
					0.125309,
					0.59561699999999995,
					323.02303918749999,
					0.65558000000000005,
					0.12972500000000001,
					0.59231699999999998,
					323.02328431249998,
					0.66037400000000002,
					0.13414400000000001,
					0.58897100000000002,
					323.02352943749997,
					0.66512899999999997,
					0.13856599999999999,
					0.58558200000000005,
					323.0237745,
					0.66984500000000002,
					0.14299200000000001,
					0.58215399999999995,
					323.02401962499999,
					0.67452199999999995,
					0.14741899999999999,
					0.57868799999999998,
					323.02426468750002,
					0.67915999999999999,
					0.15184800000000001,
					0.57518899999999995,
					323.02450981250001,
					0.68375799999999998,
					0.156278,
					0.57165999999999995,
					323.02475487499999,
					0.68831799999999999,
					0.16070899999999999,
					0.56810300000000002,
					323.02499999999998,
					0.69284000000000001,
					0.16514100000000001,
					0.56452199999999997,
					323.02524512500003,
					0.69732400000000005,
					0.169573,
					0.56091899999999995,
					323.0254901875,
					0.70176899999999998,
					0.17400499999999999,
					0.55729600000000001,
					323.02573531249999,
					0.70617799999999997,
					0.17843700000000001,
					0.55365699999999995,
					323.02598037500002,
					0.71054899999999999,
					0.182868,
					0.55000400000000005,
					323.02622550000001,
					0.71488300000000005,
					0.18729899999999999,
					0.54633799999999999,
					323.02647056249998,
					0.71918099999999996,
					0.19172900000000001,
					0.54266300000000001,
					323.02671568749997,
					0.72344399999999998,
					0.196158,
					0.53898100000000004,
					323.02696081250002,
					0.72767000000000004,
					0.20058599999999999,
					0.53529300000000002,
					323.02720587499999,
					0.73186200000000001,
					0.205013,
					0.53160099999999999,
					323.02745099999999,
					0.73601899999999998,
					0.20943899999999999,
					0.52790800000000004,
					323.02769606250001,
					0.740143,
					0.213864,
					0.52421600000000002,
					323.02794118750001,
					0.744232,
					0.21828800000000001,
					0.52052399999999999,
					323.02818624999998,
					0.74828899999999998,
					0.22271099999999999,
					0.51683400000000002,
					323.02843137500003,
					0.75231199999999998,
					0.227133,
					0.51314899999999997,
					323.02867650000002,
					0.75630399999999998,
					0.23155500000000001,
					0.50946800000000003,
					323.02892156249999,
					0.76026400000000005,
					0.23597599999999999,
					0.50579399999999997,
					323.02916668749998,
					0.76419300000000001,
					0.240396,
					0.50212599999999996,
					323.02941175000001,
					0.76809000000000005,
					0.24481700000000001,
					0.49846499999999999,
					323.029656875,
					0.77195800000000003,
					0.24923699999999999,
					0.494813,
					323.02990193749997,
					0.77579600000000004,
					0.25365799999999999,
					0.49117100000000002,
					323.03014706250002,
					0.77960399999999996,
					0.25807799999999997,
					0.487539,
					323.03039218750001,
					0.78338300000000005,
					0.26250000000000001,
					0.48391800000000001,
					323.03063724999998,
					0.78713299999999997,
					0.26692199999999999,
					0.48030699999999998,
					323.03088237499998,
					0.79085499999999997,
					0.271345,
					0.47670600000000002,
					323.0311274375,
					0.79454899999999995,
					0.27577000000000002,
					0.47311700000000001,
					323.0313725625,
					0.79821600000000004,
					0.28019699999999997,
					0.46953800000000001,
					323.03161762500002,
					0.80185499999999998,
					0.28462599999999999,
					0.46597100000000002,
					323.03186275000002,
					0.80546700000000004,
					0.28905700000000001,
					0.46241500000000002,
					323.03210781249999,
					0.80905199999999999,
					0.293491,
					0.45887,
					323.03235293749998,
					0.812612,
					0.29792800000000003,
					0.45533800000000002,
					323.03259806250003,
					0.81614399999999998,
					0.30236800000000003,
					0.451816,
					323.032843125,
					0.81965100000000002,
					0.30681199999999997,
					0.44830599999999998,
					323.03308824999999,
					0.82313199999999997,
					0.31126100000000001,
					0.44480599999999998,
					323.03333331250002,
					0.82658799999999999,
					0.31571399999999999,
					0.44131599999999999,
					323.03357843750001,
					0.83001800000000003,
					0.32017200000000001,
					0.437836,
					323.03382349999998,
					0.833422,
					0.32463500000000001,
					0.43436599999999997,
					323.03406862499997,
					0.83680100000000002,
					0.32910499999999998,
					0.43090499999999998,
					323.03431375000002,
					0.84015499999999999,
					0.33357999999999999,
					0.42745499999999997,
					323.03455881249999,
					0.84348400000000001,
					0.33806199999999997,
					0.42401299999999997,
					323.03480393749999,
					0.84678799999999999,
					0.34255099999999999,
					0.42057899999999998,
					323.03504900000001,
					0.85006599999999999,
					0.34704800000000002,
					0.417153,
					323.03529412500001,
					0.85331900000000005,
					0.351553,
					0.41373399999999999,
					323.03553918749998,
					0.85654699999999995,
					0.35606599999999999,
					0.41032200000000002,
					323.03578431250003,
					0.85975000000000001,
					0.36058800000000002,
					0.40691699999999997,
					323.03602943750002,
					0.862927,
					0.36511900000000003,
					0.40351900000000002,
					323.03627449999999,
					0.86607800000000001,
					0.36965999999999999,
					0.40012599999999998,
					323.03651962499998,
					0.86920299999999995,
					0.37421199999999999,
					0.39673799999999998,
					323.03676468750001,
					0.87230300000000005,
					0.378774,
					0.39335500000000001,
					323.0370098125,
					0.87537600000000004,
					0.38334699999999999,
					0.38997599999999999,
					323.03725487499997,
					0.87842299999999995,
					0.387932,
					0.3866,
					323.03750000000002,
					0.88144299999999998,
					0.39252900000000002,
					0.38322899999999999,
					323.03774512500001,
					0.884436,
					0.39713900000000002,
					0.37985999999999998,
					323.03799018749999,
					0.88740200000000002,
					0.40176200000000001,
					0.376494,
					323.03823531249998,
					0.89034000000000002,
					0.40639799999999998,
					0.37313000000000002,
					323.03848037500001,
					0.89324999999999999,
					0.41104800000000002,
					0.36976799999999999,
					323.0387255,
					0.89613100000000001,
					0.41571200000000003,
					0.36640699999999998,
					323.03897056250003,
					0.89898400000000001,
					0.42039199999999999,
					0.36304700000000001,
					323.03921568750002,
					0.90180700000000003,
					0.42508699999999999,
					0.35968800000000001,
					323.03946081250001,
					0.90460099999999999,
					0.42979699999999998,
					0.35632900000000001,
					323.03970587499998,
					0.90736499999999998,
					0.43452400000000002,
					0.35297000000000001,
					323.03995099999997,
					0.91009799999999996,
					0.43926799999999999,
					0.34960999999999998,
					323.0401960625,
					0.91279999999999994,
					0.44402900000000001,
					0.34625099999999998,
					323.04044118749999,
					0.91547100000000003,
					0.44880700000000001,
					0.34288999999999997,
					323.04068625000002,
					0.91810899999999995,
					0.45360299999999998,
					0.33952900000000003,
					323.04093137500001,
					0.92071400000000003,
					0.45841700000000002,
					0.33616600000000002,
					323.04117650000001,
					0.92328699999999997,
					0.46325100000000002,
					0.33280100000000001,
					323.04142156249998,
					0.92582500000000001,
					0.46810299999999999,
					0.32943499999999998,
					323.04166668750003,
					0.92832899999999996,
					0.47297499999999998,
					0.326067,
					323.04191175,
					0.93079800000000001,
					0.47786699999999999,
					0.32269700000000001,
					323.04215687499999,
					0.93323199999999995,
					0.48277999999999999,
					0.31932500000000003,
					323.04240193750002,
					0.93562999999999996,
					0.48771199999999998,
					0.31595200000000001,
					323.04264706250001,
					0.93798999999999999,
					0.49266700000000002,
					0.31257499999999999,
					323.0428921875,
					0.94031299999999995,
					0.49764199999999997,
					0.309197,
					323.04313724999997,
					0.94259800000000005,
					0.50263899999999995,
					0.30581599999999998,
					323.04338237500002,
					0.94484400000000002,
					0.50765800000000005,
					0.30243300000000001,
					323.04362743749999,
					0.94705099999999998,
					0.51269900000000002,
					0.29904900000000001,
					323.04387256249998,
					0.94921699999999998,
					0.51776299999999997,
					0.29566199999999998,
					323.04411762500001,
					0.95134399999999997,
					0.52285000000000004,
					0.29227500000000001,
					323.04436275,
					0.95342800000000005,
					0.52795999999999998,
					0.288883,
					323.04460781249998,
					0.95547000000000004,
					0.53309300000000004,
					0.28549000000000002,
					323.04485293750002,
					0.95746900000000001,
					0.53825000000000001,
					0.28209600000000001,
					323.04509806250002,
					0.95942400000000005,
					0.543431,
					0.27870099999999998,
					323.04534312499999,
					0.96133599999999997,
					0.54863600000000001,
					0.27530500000000002,
					323.04558824999998,
					0.96320300000000003,
					0.55386500000000005,
					0.27190900000000001,
					323.04583331250001,
					0.96502399999999999,
					0.559118,
					0.268513,
					323.0460784375,
					0.96679800000000005,
					0.56439600000000001,
					0.26511800000000002,
					323.04632350000003,
					0.968526,
					0.56969999999999998,
					0.26172099999999998,
					323.04656862500002,
					0.97020499999999998,
					0.57502799999999998,
					0.25832500000000003,
					323.04681375000001,
					0.971835,
					0.58038199999999995,
					0.25493100000000002,
					323.04705881249998,
					0.97341599999999995,
					0.58576099999999998,
					0.25153999999999999,
					323.04730393749998,
					0.97494700000000001,
					0.59116500000000005,
					0.24815100000000001,
					323.047549,
					0.97642799999999996,
					0.59659499999999999,
					0.24476700000000001,
					323.047794125,
					0.97785599999999995,
					0.602051,
					0.24138699999999999,
					323.04803918750002,
					0.97923300000000002,
					0.60753199999999996,
					0.238013,
					323.04828431250002,
					0.98055599999999998,
					0.613039,
					0.23464599999999999,
					323.04852943750001,
					0.98182599999999998,
					0.61857200000000001,
					0.23128699999999999,
					323.04877449999998,
					0.98304100000000005,
					0.62413099999999999,
					0.227937,
					323.04901962500003,
					0.98419900000000005,
					0.629718,
					0.22459499999999999,
					323.0492646875,
					0.98530099999999998,
					0.63532999999999995,
					0.22126499999999999,
					323.04950981249999,
					0.98634500000000003,
					0.64096900000000001,
					0.217948,
					323.04975487500002,
					0.98733199999999999,
					0.64663300000000001,
					0.21464800000000001,
					323.05000000000001,
					0.98826000000000003,
					0.65232500000000004,
					0.211364,
					323.050245125,
					0.98912800000000001,
					0.65804300000000004,
					0.20810000000000001,
					323.05049018749997,
					0.98993500000000001,
					0.66378700000000002,
					0.20485900000000001,
					323.05073531250002,
					0.99068100000000003,
					0.66955799999999999,
					0.20164199999999999,
					323.05098037499999,
					0.99136500000000005,
					0.67535500000000004,
					0.19845299999999999,
					323.05122549999999,
					0.99198500000000001,
					0.68117899999999998,
					0.195295,
					323.05147056250001,
					0.99254100000000001,
					0.68703000000000003,
					0.19217000000000001,
					323.05171568750001,
					0.99303200000000003,
					0.69290700000000005,
					0.189084,
					323.0519608125,
					0.99345600000000001,
					0.69881000000000004,
					0.18604100000000001,
					323.05220587500003,
					0.99381399999999998,
					0.70474099999999995,
					0.18304300000000001,
					323.05245100000002,
					0.99410299999999996,
					0.71069800000000005,
					0.18009700000000001,
					323.05269606249999,
					0.99432399999999999,
					0.71668100000000001,
					0.177208,
					323.05294118749998,
					0.99447399999999997,
					0.72269099999999997,
					0.17438100000000001,
					323.05318625000001,
					0.99455300000000002,
					0.72872800000000004,
					0.171622,
					323.053431375,
					0.99456100000000003,
					0.73479099999999997,
					0.168938,
					323.05367649999999,
					0.99449500000000002,
					0.74087999999999998,
					0.16633500000000001,
					323.05392156250002,
					0.99435499999999999,
					0.74699499999999996,
					0.16382099999999999,
					323.05416668750001,
					0.99414100000000005,
					0.75313699999999995,
					0.16140399999999999,
					323.05441174999999,
					0.99385100000000004,
					0.75930399999999998,
					0.15909200000000001,
					323.05465687499998,
					0.99348199999999998,
					0.76549900000000004,
					0.156891,
					323.05490193750001,
					0.99303300000000005,
					0.77171999999999996,
					0.154808,
					323.0551470625,
					0.99250499999999997,
					0.77796699999999996,
					0.15285499999999999,
					323.05539218749999,
					0.99189700000000003,
					0.78423900000000002,
					0.15104200000000001,
					323.05563725000002,
					0.99120900000000001,
					0.79053700000000005,
					0.14937700000000001,
					323.05588237500001,
					0.99043899999999996,
					0.79685899999999998,
					0.14787,
					323.05612743749998,
					0.98958699999999999,
					0.80320499999999995,
					0.14652899999999999,
					323.05637256249997,
					0.98864799999999997,
					0.80957900000000005,
					0.14535699999999999,
					323.056617625,
					0.98762099999999997,
					0.81597799999999998,
					0.14436299999999999,
					323.05686274999999,
					0.98650899999999997,
					0.82240100000000005,
					0.14355699999999999,
					323.05710781250002,
					0.98531400000000002,
					0.82884599999999997,
					0.14294499999999999,
					323.05735293750001,
					0.98403099999999999,
					0.83531500000000003,
					0.14252799999999999,
					323.05759806250001,
					0.982653,
					0.841812,
					0.14230300000000001,
					323.05784312499998,
					0.98119000000000001,
					0.848329,
					0.14227899999999999,
					323.05808825000003,
					0.97964399999999996,
					0.85486600000000001,
					0.142453,
					323.0583333125,
					0.97799499999999995,
					0.86143199999999998,
					0.14280799999999999,
					323.05857843749999,
					0.97626500000000005,
					0.86801600000000001,
					0.14335100000000001,
					323.05882350000002,
					0.97444299999999995,
					0.87462200000000001,
					0.14406099999999999,
					323.05906862500001,
					0.97253000000000001,
					0.88124999999999998,
					0.144923,
					323.05931375,
					0.97053299999999998,
					0.88789600000000002,
					0.14591899999999999,
					323.05955881249997,
					0.96844300000000005,
					0.89456400000000003,
					0.14701400000000001,
					323.05980393750002,
					0.96627099999999999,
					0.90124899999999997,
					0.14818000000000001,
					323.06004899999999,
					0.96402100000000002,
					0.90795000000000003,
					0.14937,
					323.06029412499998,
					0.96168100000000001,
					0.91467200000000004,
					0.15051999999999999,
					323.06053918750001,
					0.95927600000000002,
					0.92140699999999998,
					0.15156600000000001,
					323.0607843125,
					0.95680799999999999,
					0.92815199999999998,
					0.15240899999999999,
					323.0610294375,
					0.954287,
					0.93490799999999996,
					0.152921,
					323.06127450000002,
					0.95172599999999996,
					0.94167100000000004,
					0.15292500000000001,
					323.06151962500002,
					0.94915099999999997,
					0.94843500000000003,
					0.15217800000000001,
					323.06176468749999,
					0.94660200000000005,
					0.95518999999999998,
					0.15032799999999999,
					323.06200981249998,
					0.94415199999999999,
					0.96191599999999999,
					0.14686099999999999,
					323.06225487500001,
					0.94189599999999996,
					0.96858999999999995,
					0.140956,
					323.0625,
					0.94001500000000004,
					0.97515799999999997,
					0.131326
				]
			}
		},
		"Tgas" : 
		{
			"PVLookupTable" : 
			{
				"ColorSpace" : 3,
				"RGBPoints" : 
				[
					323.0,
					0.050382999999999997,
					0.029803,
					0.52797499999999997,
					323.00024512499999,
					0.063535999999999995,
					0.028426,
					0.53312400000000004,
					323.00049018750002,
					0.075353000000000003,
					0.027206000000000001,
					0.53800700000000001,
					323.00073531250001,
					0.086221999999999993,
					0.026124999999999999,
					0.54265799999999997,
					323.00098037499998,
					0.096379000000000006,
					0.025165,
					0.54710300000000001,
					323.00122549999998,
					0.10598,
					0.024309000000000001,
					0.55136799999999997,
					323.0014705625,
					0.115124,
					0.023556000000000001,
					0.55546799999999996,
					323.0017156875,
					0.123903,
					0.022877999999999999,
					0.559423,
					323.00196081249999,
					0.132381,
					0.022258,
					0.56325000000000003,
					323.00220587500002,
					0.14060300000000001,
					0.021687000000000001,
					0.56695899999999999,
					323.00245100000001,
					0.14860699999999999,
					0.021153999999999999,
					0.57056200000000001,
					323.00269606249998,
					0.156421,
					0.020650999999999999,
					0.57406500000000005,
					323.00294118750003,
					0.16406999999999999,
					0.020171000000000001,
					0.57747800000000005,
					323.00318625,
					0.171574,
					0.019706000000000001,
					0.58080600000000004,
					323.00343137499999,
					0.17895,
					0.019251999999999998,
					0.58405399999999996,
					323.00367649999998,
					0.18621299999999999,
					0.018803,
					0.58722799999999997,
					323.00392156250001,
					0.19337399999999999,
					0.018353999999999999,
					0.59033000000000002,
					323.0041666875,
					0.20044500000000001,
					0.017902000000000001,
					0.593364,
					323.00441174999997,
					0.20743500000000001,
					0.017441999999999999,
					0.596333,
					323.00465687500002,
					0.21435000000000001,
					0.016972999999999999,
					0.59923899999999997,
					323.00490193749999,
					0.221197,
					0.016497000000000001,
					0.60208300000000003,
					323.00514706249999,
					0.22798299999999999,
					0.016007,
					0.60486700000000004,
					323.00539218749998,
					0.23471500000000001,
					0.015502,
					0.60759200000000002,
					323.00563725000001,
					0.241396,
					0.014978999999999999,
					0.610259,
					323.005882375,
					0.248032,
					0.014439,
					0.61286799999999997,
					323.00612743750003,
					0.25462699999999999,
					0.013882,
					0.61541900000000005,
					323.00637256250002,
					0.261183,
					0.013308,
					0.61791099999999999,
					323.00661762499999,
					0.26770300000000002,
					0.012716,
					0.62034599999999995,
					323.00686274999998,
					0.27419100000000002,
					0.012109,
					0.622722,
					323.00710781250001,
					0.28064800000000001,
					0.011488,
					0.62503799999999998,
					323.0073529375,
					0.287076,
					0.010855,
					0.62729500000000005,
					323.00759806249999,
					0.29347800000000002,
					0.010213,
					0.62948999999999999,
					323.00784312500002,
					0.29985499999999998,
					0.0095610000000000001,
					0.63162399999999996,
					323.00808825000001,
					0.30620999999999998,
					0.0089020000000000002,
					0.63369399999999998,
					323.00833331249999,
					0.31254300000000002,
					0.0082389999999999998,
					0.63570000000000004,
					323.00857843749998,
					0.31885599999999997,
					0.0075760000000000003,
					0.63763999999999998,
					323.00882350000001,
					0.32514999999999999,
					0.0069150000000000001,
					0.63951199999999997,
					323.009068625,
					0.331426,
					0.0062610000000000001,
					0.641316,
					323.00931374999999,
					0.33768300000000001,
					0.0056179999999999997,
					0.64304899999999998,
					323.00955881250002,
					0.34392499999999998,
					0.0049909999999999998,
					0.64471000000000001,
					323.00980393750001,
					0.35015000000000002,
					0.0043819999999999996,
					0.64629800000000004,
					323.01004899999998,
					0.35635899999999998,
					0.0037980000000000002,
					0.64781,
					323.01029412499997,
					0.36255300000000001,
					0.0032429999999999998,
					0.64924499999999996,
					323.0105391875,
					0.36873299999999998,
					0.0027239999999999999,
					0.65060099999999998,
					323.01078431249999,
					0.37489699999999998,
					0.002245,
					0.65187600000000001,
					323.01102943749999,
					0.38104700000000002,
					0.0018140000000000001,
					0.65306799999999998,
					323.01127450000001,
					0.387183,
					0.0014339999999999999,
					0.65417700000000001,
					323.01151962500001,
					0.39330399999999999,
					0.001114,
					0.65519899999999998,
					323.01176468749998,
					0.39941100000000002,
					0.00085899999999999995,
					0.65613299999999997,
					323.01200981250003,
					0.405503,
					0.000678,
					0.65697700000000003,
					323.012254875,
					0.41158,
					0.00057700000000000004,
					0.65773000000000004,
					323.01249999999999,
					0.41764200000000001,
					0.00056400000000000005,
					0.65839000000000003,
					323.01274512499998,
					0.42368899999999998,
					0.00064599999999999998,
					0.65895599999999999,
					323.01299018750001,
					0.42971900000000002,
					0.00083100000000000003,
					0.65942500000000004,
					323.0132353125,
					0.43573400000000001,
					0.001127,
					0.65979699999999997,
					323.01348037499997,
					0.44173200000000001,
					0.0015399999999999999,
					0.66006900000000002,
					323.01372550000002,
					0.447714,
					0.0020799999999999998,
					0.66024000000000005,
					323.01397056249999,
					0.453677,
					0.0027550000000000001,
					0.66030999999999995,
					323.01421568749998,
					0.459623,
					0.0035739999999999999,
					0.660277,
					323.01446081249998,
					0.46555000000000002,
					0.0045450000000000004,
					0.66013900000000003,
					323.014705875,
					0.47145700000000001,
					0.0056779999999999999,
					0.65989699999999996,
					323.014951,
					0.47734399999999999,
					0.0069800000000000001,
					0.65954900000000005,
					323.01519606250002,
					0.48320999999999997,
					0.0084600000000000005,
					0.65909499999999999,
					323.01544118750002,
					0.48905500000000002,
					0.010127000000000001,
					0.65853399999999995,
					323.01568624999999,
					0.49487700000000001,
					0.011990000000000001,
					0.65786500000000003,
					323.01593137499998,
					0.50067799999999996,
					0.014055,
					0.65708800000000001,
					323.01617649999997,
					0.50645399999999996,
					0.016333,
					0.65620199999999995,
					323.0164215625,
					0.51220600000000005,
					0.018832999999999999,
					0.65520900000000004,
					323.01666668749999,
					0.51793299999999998,
					0.021562999999999999,
					0.65410900000000005,
					323.01691175000002,
					0.52363300000000002,
					0.024532000000000002,
					0.65290099999999995,
					323.01715687500001,
					0.52930600000000005,
					0.027747000000000001,
					0.651586,
					323.01740193749998,
					0.53495199999999998,
					0.031217000000000002,
					0.65016499999999999,
					323.01764706249998,
					0.54056999999999999,
					0.034950000000000002,
					0.64863999999999999,
					323.01789218750002,
					0.546157,
					0.038954000000000003,
					0.64700999999999997,
					323.01813725,
					0.55171499999999996,
					0.043136000000000001,
					0.64527699999999999,
					323.01838237499999,
					0.55724300000000004,
					0.047330999999999998,
					0.64344299999999999,
					323.01862743750002,
					0.56273799999999996,
					0.051545000000000001,
					0.641509,
					323.01887256250001,
					0.56820099999999996,
					0.055778000000000001,
					0.63947699999999996,
					323.01911762499998,
					0.57363200000000003,
					0.060027999999999998,
					0.63734900000000005,
					323.01936275000003,
					0.57902900000000002,
					0.064296000000000006,
					0.63512599999999997,
					323.0196078125,
					0.58439099999999999,
					0.068579000000000001,
					0.63281200000000004,
					323.01985293749999,
					0.58971899999999999,
					0.072877999999999998,
					0.63040799999999997,
					323.02009806249998,
					0.59501099999999996,
					0.077189999999999995,
					0.62791699999999995,
					323.02034312500001,
					0.60026599999999997,
					0.081516000000000005,
					0.62534199999999995,
					323.02058825,
					0.60548500000000005,
					0.085854,
					0.62268599999999996,
					323.02083331249997,
					0.61066699999999996,
					0.090204000000000006,
					0.61995100000000003,
					323.02107843750002,
					0.61581200000000003,
					0.094563999999999995,
					0.61714000000000002,
					323.02132349999999,
					0.620919,
					0.098933999999999994,
					0.61425700000000005,
					323.02156862499999,
					0.62598699999999996,
					0.103312,
					0.61130499999999999,
					323.02181374999998,
					0.63101700000000005,
					0.107699,
					0.60828700000000002,
					323.02205881250001,
					0.63600800000000002,
					0.112092,
					0.60520499999999999,
					323.0223039375,
					0.64095899999999995,
					0.116492,
					0.60206499999999996,
					323.02254900000003,
					0.645872,
					0.12089800000000001,
					0.59886700000000004,
					323.02279412500002,
					0.65074600000000005,
					0.125309,
					0.59561699999999995,
					323.02303918749999,
					0.65558000000000005,
					0.12972500000000001,
					0.59231699999999998,
					323.02328431249998,
					0.66037400000000002,
					0.13414400000000001,
					0.58897100000000002,
					323.02352943749997,
					0.66512899999999997,
					0.13856599999999999,
					0.58558200000000005,
					323.0237745,
					0.66984500000000002,
					0.14299200000000001,
					0.58215399999999995,
					323.02401962499999,
					0.67452199999999995,
					0.14741899999999999,
					0.57868799999999998,
					323.02426468750002,
					0.67915999999999999,
					0.15184800000000001,
					0.57518899999999995,
					323.02450981250001,
					0.68375799999999998,
					0.156278,
					0.57165999999999995,
					323.02475487499999,
					0.68831799999999999,
					0.16070899999999999,
					0.56810300000000002,
					323.02499999999998,
					0.69284000000000001,
					0.16514100000000001,
					0.56452199999999997,
					323.02524512500003,
					0.69732400000000005,
					0.169573,
					0.56091899999999995,
					323.0254901875,
					0.70176899999999998,
					0.17400499999999999,
					0.55729600000000001,
					323.02573531249999,
					0.70617799999999997,
					0.17843700000000001,
					0.55365699999999995,
					323.02598037500002,
					0.71054899999999999,
					0.182868,
					0.55000400000000005,
					323.02622550000001,
					0.71488300000000005,
					0.18729899999999999,
					0.54633799999999999,
					323.02647056249998,
					0.71918099999999996,
					0.19172900000000001,
					0.54266300000000001,
					323.02671568749997,
					0.72344399999999998,
					0.196158,
					0.53898100000000004,
					323.02696081250002,
					0.72767000000000004,
					0.20058599999999999,
					0.53529300000000002,
					323.02720587499999,
					0.73186200000000001,
					0.205013,
					0.53160099999999999,
					323.02745099999999,
					0.73601899999999998,
					0.20943899999999999,
					0.52790800000000004,
					323.02769606250001,
					0.740143,
					0.213864,
					0.52421600000000002,
					323.02794118750001,
					0.744232,
					0.21828800000000001,
					0.52052399999999999,
					323.02818624999998,
					0.74828899999999998,
					0.22271099999999999,
					0.51683400000000002,
					323.02843137500003,
					0.75231199999999998,
					0.227133,
					0.51314899999999997,
					323.02867650000002,
					0.75630399999999998,
					0.23155500000000001,
					0.50946800000000003,
					323.02892156249999,
					0.76026400000000005,
					0.23597599999999999,
					0.50579399999999997,
					323.02916668749998,
					0.76419300000000001,
					0.240396,
					0.50212599999999996,
					323.02941175000001,
					0.76809000000000005,
					0.24481700000000001,
					0.49846499999999999,
					323.029656875,
					0.77195800000000003,
					0.24923699999999999,
					0.494813,
					323.02990193749997,
					0.77579600000000004,
					0.25365799999999999,
					0.49117100000000002,
					323.03014706250002,
					0.77960399999999996,
					0.25807799999999997,
					0.487539,
					323.03039218750001,
					0.78338300000000005,
					0.26250000000000001,
					0.48391800000000001,
					323.03063724999998,
					0.78713299999999997,
					0.26692199999999999,
					0.48030699999999998,
					323.03088237499998,
					0.79085499999999997,
					0.271345,
					0.47670600000000002,
					323.0311274375,
					0.79454899999999995,
					0.27577000000000002,
					0.47311700000000001,
					323.0313725625,
					0.79821600000000004,
					0.28019699999999997,
					0.46953800000000001,
					323.03161762500002,
					0.80185499999999998,
					0.28462599999999999,
					0.46597100000000002,
					323.03186275000002,
					0.80546700000000004,
					0.28905700000000001,
					0.46241500000000002,
					323.03210781249999,
					0.80905199999999999,
					0.293491,
					0.45887,
					323.03235293749998,
					0.812612,
					0.29792800000000003,
					0.45533800000000002,
					323.03259806250003,
					0.81614399999999998,
					0.30236800000000003,
					0.451816,
					323.032843125,
					0.81965100000000002,
					0.30681199999999997,
					0.44830599999999998,
					323.03308824999999,
					0.82313199999999997,
					0.31126100000000001,
					0.44480599999999998,
					323.03333331250002,
					0.82658799999999999,
					0.31571399999999999,
					0.44131599999999999,
					323.03357843750001,
					0.83001800000000003,
					0.32017200000000001,
					0.437836,
					323.03382349999998,
					0.833422,
					0.32463500000000001,
					0.43436599999999997,
					323.03406862499997,
					0.83680100000000002,
					0.32910499999999998,
					0.43090499999999998,
					323.03431375000002,
					0.84015499999999999,
					0.33357999999999999,
					0.42745499999999997,
					323.03455881249999,
					0.84348400000000001,
					0.33806199999999997,
					0.42401299999999997,
					323.03480393749999,
					0.84678799999999999,
					0.34255099999999999,
					0.42057899999999998,
					323.03504900000001,
					0.85006599999999999,
					0.34704800000000002,
					0.417153,
					323.03529412500001,
					0.85331900000000005,
					0.351553,
					0.41373399999999999,
					323.03553918749998,
					0.85654699999999995,
					0.35606599999999999,
					0.41032200000000002,
					323.03578431250003,
					0.85975000000000001,
					0.36058800000000002,
					0.40691699999999997,
					323.03602943750002,
					0.862927,
					0.36511900000000003,
					0.40351900000000002,
					323.03627449999999,
					0.86607800000000001,
					0.36965999999999999,
					0.40012599999999998,
					323.03651962499998,
					0.86920299999999995,
					0.37421199999999999,
					0.39673799999999998,
					323.03676468750001,
					0.87230300000000005,
					0.378774,
					0.39335500000000001,
					323.0370098125,
					0.87537600000000004,
					0.38334699999999999,
					0.38997599999999999,
					323.03725487499997,
					0.87842299999999995,
					0.387932,
					0.3866,
					323.03750000000002,
					0.88144299999999998,
					0.39252900000000002,
					0.38322899999999999,
					323.03774512500001,
					0.884436,
					0.39713900000000002,
					0.37985999999999998,
					323.03799018749999,
					0.88740200000000002,
					0.40176200000000001,
					0.376494,
					323.03823531249998,
					0.89034000000000002,
					0.40639799999999998,
					0.37313000000000002,
					323.03848037500001,
					0.89324999999999999,
					0.41104800000000002,
					0.36976799999999999,
					323.0387255,
					0.89613100000000001,
					0.41571200000000003,
					0.36640699999999998,
					323.03897056250003,
					0.89898400000000001,
					0.42039199999999999,
					0.36304700000000001,
					323.03921568750002,
					0.90180700000000003,
					0.42508699999999999,
					0.35968800000000001,
					323.03946081250001,
					0.90460099999999999,
					0.42979699999999998,
					0.35632900000000001,
					323.03970587499998,
					0.90736499999999998,
					0.43452400000000002,
					0.35297000000000001,
					323.03995099999997,
					0.91009799999999996,
					0.43926799999999999,
					0.34960999999999998,
					323.0401960625,
					0.91279999999999994,
					0.44402900000000001,
					0.34625099999999998,
					323.04044118749999,
					0.91547100000000003,
					0.44880700000000001,
					0.34288999999999997,
					323.04068625000002,
					0.91810899999999995,
					0.45360299999999998,
					0.33952900000000003,
					323.04093137500001,
					0.92071400000000003,
					0.45841700000000002,
					0.33616600000000002,
					323.04117650000001,
					0.92328699999999997,
					0.46325100000000002,
					0.33280100000000001,
					323.04142156249998,
					0.92582500000000001,
					0.46810299999999999,
					0.32943499999999998,
					323.04166668750003,
					0.92832899999999996,
					0.47297499999999998,
					0.326067,
					323.04191175,
					0.93079800000000001,
					0.47786699999999999,
					0.32269700000000001,
					323.04215687499999,
					0.93323199999999995,
					0.48277999999999999,
					0.31932500000000003,
					323.04240193750002,
					0.93562999999999996,
					0.48771199999999998,
					0.31595200000000001,
					323.04264706250001,
					0.93798999999999999,
					0.49266700000000002,
					0.31257499999999999,
					323.0428921875,
					0.94031299999999995,
					0.49764199999999997,
					0.309197,
					323.04313724999997,
					0.94259800000000005,
					0.50263899999999995,
					0.30581599999999998,
					323.04338237500002,
					0.94484400000000002,
					0.50765800000000005,
					0.30243300000000001,
					323.04362743749999,
					0.94705099999999998,
					0.51269900000000002,
					0.29904900000000001,
					323.04387256249998,
					0.94921699999999998,
					0.51776299999999997,
					0.29566199999999998,
					323.04411762500001,
					0.95134399999999997,
					0.52285000000000004,
					0.29227500000000001,
					323.04436275,
					0.95342800000000005,
					0.52795999999999998,
					0.288883,
					323.04460781249998,
					0.95547000000000004,
					0.53309300000000004,
					0.28549000000000002,
					323.04485293750002,
					0.95746900000000001,
					0.53825000000000001,
					0.28209600000000001,
					323.04509806250002,
					0.95942400000000005,
					0.543431,
					0.27870099999999998,
					323.04534312499999,
					0.96133599999999997,
					0.54863600000000001,
					0.27530500000000002,
					323.04558824999998,
					0.96320300000000003,
					0.55386500000000005,
					0.27190900000000001,
					323.04583331250001,
					0.96502399999999999,
					0.559118,
					0.268513,
					323.0460784375,
					0.96679800000000005,
					0.56439600000000001,
					0.26511800000000002,
					323.04632350000003,
					0.968526,
					0.56969999999999998,
					0.26172099999999998,
					323.04656862500002,
					0.97020499999999998,
					0.57502799999999998,
					0.25832500000000003,
					323.04681375000001,
					0.971835,
					0.58038199999999995,
					0.25493100000000002,
					323.04705881249998,
					0.97341599999999995,
					0.58576099999999998,
					0.25153999999999999,
					323.04730393749998,
					0.97494700000000001,
					0.59116500000000005,
					0.24815100000000001,
					323.047549,
					0.97642799999999996,
					0.59659499999999999,
					0.24476700000000001,
					323.047794125,
					0.97785599999999995,
					0.602051,
					0.24138699999999999,
					323.04803918750002,
					0.97923300000000002,
					0.60753199999999996,
					0.238013,
					323.04828431250002,
					0.98055599999999998,
					0.613039,
					0.23464599999999999,
					323.04852943750001,
					0.98182599999999998,
					0.61857200000000001,
					0.23128699999999999,
					323.04877449999998,
					0.98304100000000005,
					0.62413099999999999,
					0.227937,
					323.04901962500003,
					0.98419900000000005,
					0.629718,
					0.22459499999999999,
					323.0492646875,
					0.98530099999999998,
					0.63532999999999995,
					0.22126499999999999,
					323.04950981249999,
					0.98634500000000003,
					0.64096900000000001,
					0.217948,
					323.04975487500002,
					0.98733199999999999,
					0.64663300000000001,
					0.21464800000000001,
					323.05000000000001,
					0.98826000000000003,
					0.65232500000000004,
					0.211364,
					323.050245125,
					0.98912800000000001,
					0.65804300000000004,
					0.20810000000000001,
					323.05049018749997,
					0.98993500000000001,
					0.66378700000000002,
					0.20485900000000001,
					323.05073531250002,
					0.99068100000000003,
					0.66955799999999999,
					0.20164199999999999,
					323.05098037499999,
					0.99136500000000005,
					0.67535500000000004,
					0.19845299999999999,
					323.05122549999999,
					0.99198500000000001,
					0.68117899999999998,
					0.195295,
					323.05147056250001,
					0.99254100000000001,
					0.68703000000000003,
					0.19217000000000001,
					323.05171568750001,
					0.99303200000000003,
					0.69290700000000005,
					0.189084,
					323.0519608125,
					0.99345600000000001,
					0.69881000000000004,
					0.18604100000000001,
					323.05220587500003,
					0.99381399999999998,
					0.70474099999999995,
					0.18304300000000001,
					323.05245100000002,
					0.99410299999999996,
					0.71069800000000005,
					0.18009700000000001,
					323.05269606249999,
					0.99432399999999999,
					0.71668100000000001,
					0.177208,
					323.05294118749998,
					0.99447399999999997,
					0.72269099999999997,
					0.17438100000000001,
					323.05318625000001,
					0.99455300000000002,
					0.72872800000000004,
					0.171622,
					323.053431375,
					0.99456100000000003,
					0.73479099999999997,
					0.168938,
					323.05367649999999,
					0.99449500000000002,
					0.74087999999999998,
					0.16633500000000001,
					323.05392156250002,
					0.99435499999999999,
					0.74699499999999996,
					0.16382099999999999,
					323.05416668750001,
					0.99414100000000005,
					0.75313699999999995,
					0.16140399999999999,
					323.05441174999999,
					0.99385100000000004,
					0.75930399999999998,
					0.15909200000000001,
					323.05465687499998,
					0.99348199999999998,
					0.76549900000000004,
					0.156891,
					323.05490193750001,
					0.99303300000000005,
					0.77171999999999996,
					0.154808,
					323.0551470625,
					0.99250499999999997,
					0.77796699999999996,
					0.15285499999999999,
					323.05539218749999,
					0.99189700000000003,
					0.78423900000000002,
					0.15104200000000001,
					323.05563725000002,
					0.99120900000000001,
					0.79053700000000005,
					0.14937700000000001,
					323.05588237500001,
					0.99043899999999996,
					0.79685899999999998,
					0.14787,
					323.05612743749998,
					0.98958699999999999,
					0.80320499999999995,
					0.14652899999999999,
					323.05637256249997,
					0.98864799999999997,
					0.80957900000000005,
					0.14535699999999999,
					323.056617625,
					0.98762099999999997,
					0.81597799999999998,
					0.14436299999999999,
					323.05686274999999,
					0.98650899999999997,
					0.82240100000000005,
					0.14355699999999999,
					323.05710781250002,
					0.98531400000000002,
					0.82884599999999997,
					0.14294499999999999,
					323.05735293750001,
					0.98403099999999999,
					0.83531500000000003,
					0.14252799999999999,
					323.05759806250001,
					0.982653,
					0.841812,
					0.14230300000000001,
					323.05784312499998,
					0.98119000000000001,
					0.848329,
					0.14227899999999999,
					323.05808825000003,
					0.97964399999999996,
					0.85486600000000001,
					0.142453,
					323.0583333125,
					0.97799499999999995,
					0.86143199999999998,
					0.14280799999999999,
					323.05857843749999,
					0.97626500000000005,
					0.86801600000000001,
					0.14335100000000001,
					323.05882350000002,
					0.97444299999999995,
					0.87462200000000001,
					0.14406099999999999,
					323.05906862500001,
					0.97253000000000001,
					0.88124999999999998,
					0.144923,
					323.05931375,
					0.97053299999999998,
					0.88789600000000002,
					0.14591899999999999,
					323.05955881249997,
					0.96844300000000005,
					0.89456400000000003,
					0.14701400000000001,
					323.05980393750002,
					0.96627099999999999,
					0.90124899999999997,
					0.14818000000000001,
					323.06004899999999,
					0.96402100000000002,
					0.90795000000000003,
					0.14937,
					323.06029412499998,
					0.96168100000000001,
					0.91467200000000004,
					0.15051999999999999,
					323.06053918750001,
					0.95927600000000002,
					0.92140699999999998,
					0.15156600000000001,
					323.0607843125,
					0.95680799999999999,
					0.92815199999999998,
					0.15240899999999999,
					323.0610294375,
					0.954287,
					0.93490799999999996,
					0.152921,
					323.06127450000002,
					0.95172599999999996,
					0.94167100000000004,
					0.15292500000000001,
					323.06151962500002,
					0.94915099999999997,
					0.94843500000000003,
					0.15217800000000001,
					323.06176468749999,
					0.94660200000000005,
					0.95518999999999998,
					0.15032799999999999,
					323.06200981249998,
					0.94415199999999999,
					0.96191599999999999,
					0.14686099999999999,
					323.06225487500001,
					0.94189599999999996,
					0.96858999999999995,
					0.140956,
					323.0625,
					0.94001500000000004,
					0.97515799999999997,
					0.131326
				]
			}
		},
		"Tliquid" : 
		{
			"PVLookupTable" : 
			{
				"ColorSpace" : 3,
				"RGBPoints" : 
				[
					323.0,
					0.050382999999999997,
					0.029803,
					0.52797499999999997,
					323.00024512499999,
					0.063535999999999995,
					0.028426,
					0.53312400000000004,
					323.00049018750002,
					0.075353000000000003,
					0.027206000000000001,
					0.53800700000000001,
					323.00073531250001,
					0.086221999999999993,
					0.026124999999999999,
					0.54265799999999997,
					323.00098037499998,
					0.096379000000000006,
					0.025165,
					0.54710300000000001,
					323.00122549999998,
					0.10598,
					0.024309000000000001,
					0.55136799999999997,
					323.0014705625,
					0.115124,
					0.023556000000000001,
					0.55546799999999996,
					323.0017156875,
					0.123903,
					0.022877999999999999,
					0.559423,
					323.00196081249999,
					0.132381,
					0.022258,
					0.56325000000000003,
					323.00220587500002,
					0.14060300000000001,
					0.021687000000000001,
					0.56695899999999999,
					323.00245100000001,
					0.14860699999999999,
					0.021153999999999999,
					0.57056200000000001,
					323.00269606249998,
					0.156421,
					0.020650999999999999,
					0.57406500000000005,
					323.00294118750003,
					0.16406999999999999,
					0.020171000000000001,
					0.57747800000000005,
					323.00318625,
					0.171574,
					0.019706000000000001,
					0.58080600000000004,
					323.00343137499999,
					0.17895,
					0.019251999999999998,
					0.58405399999999996,
					323.00367649999998,
					0.18621299999999999,
					0.018803,
					0.58722799999999997,
					323.00392156250001,
					0.19337399999999999,
					0.018353999999999999,
					0.59033000000000002,
					323.0041666875,
					0.20044500000000001,
					0.017902000000000001,
					0.593364,
					323.00441174999997,
					0.20743500000000001,
					0.017441999999999999,
					0.596333,
					323.00465687500002,
					0.21435000000000001,
					0.016972999999999999,
					0.59923899999999997,
					323.00490193749999,
					0.221197,
					0.016497000000000001,
					0.60208300000000003,
					323.00514706249999,
					0.22798299999999999,
					0.016007,
					0.60486700000000004,
					323.00539218749998,
					0.23471500000000001,
					0.015502,
					0.60759200000000002,
					323.00563725000001,
					0.241396,
					0.014978999999999999,
					0.610259,
					323.005882375,
					0.248032,
					0.014439,
					0.61286799999999997,
					323.00612743750003,
					0.25462699999999999,
					0.013882,
					0.61541900000000005,
					323.00637256250002,
					0.261183,
					0.013308,
					0.61791099999999999,
					323.00661762499999,
					0.26770300000000002,
					0.012716,
					0.62034599999999995,
					323.00686274999998,
					0.27419100000000002,
					0.012109,
					0.622722,
					323.00710781250001,
					0.28064800000000001,
					0.011488,
					0.62503799999999998,
					323.0073529375,
					0.287076,
					0.010855,
					0.62729500000000005,
					323.00759806249999,
					0.29347800000000002,
					0.010213,
					0.62948999999999999,
					323.00784312500002,
					0.29985499999999998,
					0.0095610000000000001,
					0.63162399999999996,
					323.00808825000001,
					0.30620999999999998,
					0.0089020000000000002,
					0.63369399999999998,
					323.00833331249999,
					0.31254300000000002,
					0.0082389999999999998,
					0.63570000000000004,
					323.00857843749998,
					0.31885599999999997,
					0.0075760000000000003,
					0.63763999999999998,
					323.00882350000001,
					0.32514999999999999,
					0.0069150000000000001,
					0.63951199999999997,
					323.009068625,
					0.331426,
					0.0062610000000000001,
					0.641316,
					323.00931374999999,
					0.33768300000000001,
					0.0056179999999999997,
					0.64304899999999998,
					323.00955881250002,
					0.34392499999999998,
					0.0049909999999999998,
					0.64471000000000001,
					323.00980393750001,
					0.35015000000000002,
					0.0043819999999999996,
					0.64629800000000004,
					323.01004899999998,
					0.35635899999999998,
					0.0037980000000000002,
					0.64781,
					323.01029412499997,
					0.36255300000000001,
					0.0032429999999999998,
					0.64924499999999996,
					323.0105391875,
					0.36873299999999998,
					0.0027239999999999999,
					0.65060099999999998,
					323.01078431249999,
					0.37489699999999998,
					0.002245,
					0.65187600000000001,
					323.01102943749999,
					0.38104700000000002,
					0.0018140000000000001,
					0.65306799999999998,
					323.01127450000001,
					0.387183,
					0.0014339999999999999,
					0.65417700000000001,
					323.01151962500001,
					0.39330399999999999,
					0.001114,
					0.65519899999999998,
					323.01176468749998,
					0.39941100000000002,
					0.00085899999999999995,
					0.65613299999999997,
					323.01200981250003,
					0.405503,
					0.000678,
					0.65697700000000003,
					323.012254875,
					0.41158,
					0.00057700000000000004,
					0.65773000000000004,
					323.01249999999999,
					0.41764200000000001,
					0.00056400000000000005,
					0.65839000000000003,
					323.01274512499998,
					0.42368899999999998,
					0.00064599999999999998,
					0.65895599999999999,
					323.01299018750001,
					0.42971900000000002,
					0.00083100000000000003,
					0.65942500000000004,
					323.0132353125,
					0.43573400000000001,
					0.001127,
					0.65979699999999997,
					323.01348037499997,
					0.44173200000000001,
					0.0015399999999999999,
					0.66006900000000002,
					323.01372550000002,
					0.447714,
					0.0020799999999999998,
					0.66024000000000005,
					323.01397056249999,
					0.453677,
					0.0027550000000000001,
					0.66030999999999995,
					323.01421568749998,
					0.459623,
					0.0035739999999999999,
					0.660277,
					323.01446081249998,
					0.46555000000000002,
					0.0045450000000000004,
					0.66013900000000003,
					323.014705875,
					0.47145700000000001,
					0.0056779999999999999,
					0.65989699999999996,
					323.014951,
					0.47734399999999999,
					0.0069800000000000001,
					0.65954900000000005,
					323.01519606250002,
					0.48320999999999997,
					0.0084600000000000005,
					0.65909499999999999,
					323.01544118750002,
					0.48905500000000002,
					0.010127000000000001,
					0.65853399999999995,
					323.01568624999999,
					0.49487700000000001,
					0.011990000000000001,
					0.65786500000000003,
					323.01593137499998,
					0.50067799999999996,
					0.014055,
					0.65708800000000001,
					323.01617649999997,
					0.50645399999999996,
					0.016333,
					0.65620199999999995,
					323.0164215625,
					0.51220600000000005,
					0.018832999999999999,
					0.65520900000000004,
					323.01666668749999,
					0.51793299999999998,
					0.021562999999999999,
					0.65410900000000005,
					323.01691175000002,
					0.52363300000000002,
					0.024532000000000002,
					0.65290099999999995,
					323.01715687500001,
					0.52930600000000005,
					0.027747000000000001,
					0.651586,
					323.01740193749998,
					0.53495199999999998,
					0.031217000000000002,
					0.65016499999999999,
					323.01764706249998,
					0.54056999999999999,
					0.034950000000000002,
					0.64863999999999999,
					323.01789218750002,
					0.546157,
					0.038954000000000003,
					0.64700999999999997,
					323.01813725,
					0.55171499999999996,
					0.043136000000000001,
					0.64527699999999999,
					323.01838237499999,
					0.55724300000000004,
					0.047330999999999998,
					0.64344299999999999,
					323.01862743750002,
					0.56273799999999996,
					0.051545000000000001,
					0.641509,
					323.01887256250001,
					0.56820099999999996,
					0.055778000000000001,
					0.63947699999999996,
					323.01911762499998,
					0.57363200000000003,
					0.060027999999999998,
					0.63734900000000005,
					323.01936275000003,
					0.57902900000000002,
					0.064296000000000006,
					0.63512599999999997,
					323.0196078125,
					0.58439099999999999,
					0.068579000000000001,
					0.63281200000000004,
					323.01985293749999,
					0.58971899999999999,
					0.072877999999999998,
					0.63040799999999997,
					323.02009806249998,
					0.59501099999999996,
					0.077189999999999995,
					0.62791699999999995,
					323.02034312500001,
					0.60026599999999997,
					0.081516000000000005,
					0.62534199999999995,
					323.02058825,
					0.60548500000000005,
					0.085854,
					0.62268599999999996,
					323.02083331249997,
					0.61066699999999996,
					0.090204000000000006,
					0.61995100000000003,
					323.02107843750002,
					0.61581200000000003,
					0.094563999999999995,
					0.61714000000000002,
					323.02132349999999,
					0.620919,
					0.098933999999999994,
					0.61425700000000005,
					323.02156862499999,
					0.62598699999999996,
					0.103312,
					0.61130499999999999,
					323.02181374999998,
					0.63101700000000005,
					0.107699,
					0.60828700000000002,
					323.02205881250001,
					0.63600800000000002,
					0.112092,
					0.60520499999999999,
					323.0223039375,
					0.64095899999999995,
					0.116492,
					0.60206499999999996,
					323.02254900000003,
					0.645872,
					0.12089800000000001,
					0.59886700000000004,
					323.02279412500002,
					0.65074600000000005,
					0.125309,
					0.59561699999999995,
					323.02303918749999,
					0.65558000000000005,
					0.12972500000000001,
					0.59231699999999998,
					323.02328431249998,
					0.66037400000000002,
					0.13414400000000001,
					0.58897100000000002,
					323.02352943749997,
					0.66512899999999997,
					0.13856599999999999,
					0.58558200000000005,
					323.0237745,
					0.66984500000000002,
					0.14299200000000001,
					0.58215399999999995,
					323.02401962499999,
					0.67452199999999995,
					0.14741899999999999,
					0.57868799999999998,
					323.02426468750002,
					0.67915999999999999,
					0.15184800000000001,
					0.57518899999999995,
					323.02450981250001,
					0.68375799999999998,
					0.156278,
					0.57165999999999995,
					323.02475487499999,
					0.68831799999999999,
					0.16070899999999999,
					0.56810300000000002,
					323.02499999999998,
					0.69284000000000001,
					0.16514100000000001,
					0.56452199999999997,
					323.02524512500003,
					0.69732400000000005,
					0.169573,
					0.56091899999999995,
					323.0254901875,
					0.70176899999999998,
					0.17400499999999999,
					0.55729600000000001,
					323.02573531249999,
					0.70617799999999997,
					0.17843700000000001,
					0.55365699999999995,
					323.02598037500002,
					0.71054899999999999,
					0.182868,
					0.55000400000000005,
					323.02622550000001,
					0.71488300000000005,
					0.18729899999999999,
					0.54633799999999999,
					323.02647056249998,
					0.71918099999999996,
					0.19172900000000001,
					0.54266300000000001,
					323.02671568749997,
					0.72344399999999998,
					0.196158,
					0.53898100000000004,
					323.02696081250002,
					0.72767000000000004,
					0.20058599999999999,
					0.53529300000000002,
					323.02720587499999,
					0.73186200000000001,
					0.205013,
					0.53160099999999999,
					323.02745099999999,
					0.73601899999999998,
					0.20943899999999999,
					0.52790800000000004,
					323.02769606250001,
					0.740143,
					0.213864,
					0.52421600000000002,
					323.02794118750001,
					0.744232,
					0.21828800000000001,
					0.52052399999999999,
					323.02818624999998,
					0.74828899999999998,
					0.22271099999999999,
					0.51683400000000002,
					323.02843137500003,
					0.75231199999999998,
					0.227133,
					0.51314899999999997,
					323.02867650000002,
					0.75630399999999998,
					0.23155500000000001,
					0.50946800000000003,
					323.02892156249999,
					0.76026400000000005,
					0.23597599999999999,
					0.50579399999999997,
					323.02916668749998,
					0.76419300000000001,
					0.240396,
					0.50212599999999996,
					323.02941175000001,
					0.76809000000000005,
					0.24481700000000001,
					0.49846499999999999,
					323.029656875,
					0.77195800000000003,
					0.24923699999999999,
					0.494813,
					323.02990193749997,
					0.77579600000000004,
					0.25365799999999999,
					0.49117100000000002,
					323.03014706250002,
					0.77960399999999996,
					0.25807799999999997,
					0.487539,
					323.03039218750001,
					0.78338300000000005,
					0.26250000000000001,
					0.48391800000000001,
					323.03063724999998,
					0.78713299999999997,
					0.26692199999999999,
					0.48030699999999998,
					323.03088237499998,
					0.79085499999999997,
					0.271345,
					0.47670600000000002,
					323.0311274375,
					0.79454899999999995,
					0.27577000000000002,
					0.47311700000000001,
					323.0313725625,
					0.79821600000000004,
					0.28019699999999997,
					0.46953800000000001,
					323.03161762500002,
					0.80185499999999998,
					0.28462599999999999,
					0.46597100000000002,
					323.03186275000002,
					0.80546700000000004,
					0.28905700000000001,
					0.46241500000000002,
					323.03210781249999,
					0.80905199999999999,
					0.293491,
					0.45887,
					323.03235293749998,
					0.812612,
					0.29792800000000003,
					0.45533800000000002,
					323.03259806250003,
					0.81614399999999998,
					0.30236800000000003,
					0.451816,
					323.032843125,
					0.81965100000000002,
					0.30681199999999997,
					0.44830599999999998,
					323.03308824999999,
					0.82313199999999997,
					0.31126100000000001,
					0.44480599999999998,
					323.03333331250002,
					0.82658799999999999,
					0.31571399999999999,
					0.44131599999999999,
					323.03357843750001,
					0.83001800000000003,
					0.32017200000000001,
					0.437836,
					323.03382349999998,
					0.833422,
					0.32463500000000001,
					0.43436599999999997,
					323.03406862499997,
					0.83680100000000002,
					0.32910499999999998,
					0.43090499999999998,
					323.03431375000002,
					0.84015499999999999,
					0.33357999999999999,
					0.42745499999999997,
					323.03455881249999,
					0.84348400000000001,
					0.33806199999999997,
					0.42401299999999997,
					323.03480393749999,
					0.84678799999999999,
					0.34255099999999999,
					0.42057899999999998,
					323.03504900000001,
					0.85006599999999999,
					0.34704800000000002,
					0.417153,
					323.03529412500001,
					0.85331900000000005,
					0.351553,
					0.41373399999999999,
					323.03553918749998,
					0.85654699999999995,
					0.35606599999999999,
					0.41032200000000002,
					323.03578431250003,
					0.85975000000000001,
					0.36058800000000002,
					0.40691699999999997,
					323.03602943750002,
					0.862927,
					0.36511900000000003,
					0.40351900000000002,
					323.03627449999999,
					0.86607800000000001,
					0.36965999999999999,
					0.40012599999999998,
					323.03651962499998,
					0.86920299999999995,
					0.37421199999999999,
					0.39673799999999998,
					323.03676468750001,
					0.87230300000000005,
					0.378774,
					0.39335500000000001,
					323.0370098125,
					0.87537600000000004,
					0.38334699999999999,
					0.38997599999999999,
					323.03725487499997,
					0.87842299999999995,
					0.387932,
					0.3866,
					323.03750000000002,
					0.88144299999999998,
					0.39252900000000002,
					0.38322899999999999,
					323.03774512500001,
					0.884436,
					0.39713900000000002,
					0.37985999999999998,
					323.03799018749999,
					0.88740200000000002,
					0.40176200000000001,
					0.376494,
					323.03823531249998,
					0.89034000000000002,
					0.40639799999999998,
					0.37313000000000002,
					323.03848037500001,
					0.89324999999999999,
					0.41104800000000002,
					0.36976799999999999,
					323.0387255,
					0.89613100000000001,
					0.41571200000000003,
					0.36640699999999998,
					323.03897056250003,
					0.89898400000000001,
					0.42039199999999999,
					0.36304700000000001,
					323.03921568750002,
					0.90180700000000003,
					0.42508699999999999,
					0.35968800000000001,
					323.03946081250001,
					0.90460099999999999,
					0.42979699999999998,
					0.35632900000000001,
					323.03970587499998,
					0.90736499999999998,
					0.43452400000000002,
					0.35297000000000001,
					323.03995099999997,
					0.91009799999999996,
					0.43926799999999999,
					0.34960999999999998,
					323.0401960625,
					0.91279999999999994,
					0.44402900000000001,
					0.34625099999999998,
					323.04044118749999,
					0.91547100000000003,
					0.44880700000000001,
					0.34288999999999997,
					323.04068625000002,
					0.91810899999999995,
					0.45360299999999998,
					0.33952900000000003,
					323.04093137500001,
					0.92071400000000003,
					0.45841700000000002,
					0.33616600000000002,
					323.04117650000001,
					0.92328699999999997,
					0.46325100000000002,
					0.33280100000000001,
					323.04142156249998,
					0.92582500000000001,
					0.46810299999999999,
					0.32943499999999998,
					323.04166668750003,
					0.92832899999999996,
					0.47297499999999998,
					0.326067,
					323.04191175,
					0.93079800000000001,
					0.47786699999999999,
					0.32269700000000001,
					323.04215687499999,
					0.93323199999999995,
					0.48277999999999999,
					0.31932500000000003,
					323.04240193750002,
					0.93562999999999996,
					0.48771199999999998,
					0.31595200000000001,
					323.04264706250001,
					0.93798999999999999,
					0.49266700000000002,
					0.31257499999999999,
					323.0428921875,
					0.94031299999999995,
					0.49764199999999997,
					0.309197,
					323.04313724999997,
					0.94259800000000005,
					0.50263899999999995,
					0.30581599999999998,
					323.04338237500002,
					0.94484400000000002,
					0.50765800000000005,
					0.30243300000000001,
					323.04362743749999,
					0.94705099999999998,
					0.51269900000000002,
					0.29904900000000001,
					323.04387256249998,
					0.94921699999999998,
					0.51776299999999997,
					0.29566199999999998,
					323.04411762500001,
					0.95134399999999997,
					0.52285000000000004,
					0.29227500000000001,
					323.04436275,
					0.95342800000000005,
					0.52795999999999998,
					0.288883,
					323.04460781249998,
					0.95547000000000004,
					0.53309300000000004,
					0.28549000000000002,
					323.04485293750002,
					0.95746900000000001,
					0.53825000000000001,
					0.28209600000000001,
					323.04509806250002,
					0.95942400000000005,
					0.543431,
					0.27870099999999998,
					323.04534312499999,
					0.96133599999999997,
					0.54863600000000001,
					0.27530500000000002,
					323.04558824999998,
					0.96320300000000003,
					0.55386500000000005,
					0.27190900000000001,
					323.04583331250001,
					0.96502399999999999,
					0.559118,
					0.268513,
					323.0460784375,
					0.96679800000000005,
					0.56439600000000001,
					0.26511800000000002,
					323.04632350000003,
					0.968526,
					0.56969999999999998,
					0.26172099999999998,
					323.04656862500002,
					0.97020499999999998,
					0.57502799999999998,
					0.25832500000000003,
					323.04681375000001,
					0.971835,
					0.58038199999999995,
					0.25493100000000002,
					323.04705881249998,
					0.97341599999999995,
					0.58576099999999998,
					0.25153999999999999,
					323.04730393749998,
					0.97494700000000001,
					0.59116500000000005,
					0.24815100000000001,
					323.047549,
					0.97642799999999996,
					0.59659499999999999,
					0.24476700000000001,
					323.047794125,
					0.97785599999999995,
					0.602051,
					0.24138699999999999,
					323.04803918750002,
					0.97923300000000002,
					0.60753199999999996,
					0.238013,
					323.04828431250002,
					0.98055599999999998,
					0.613039,
					0.23464599999999999,
					323.04852943750001,
					0.98182599999999998,
					0.61857200000000001,
					0.23128699999999999,
					323.04877449999998,
					0.98304100000000005,
					0.62413099999999999,
					0.227937,
					323.04901962500003,
					0.98419900000000005,
					0.629718,
					0.22459499999999999,
					323.0492646875,
					0.98530099999999998,
					0.63532999999999995,
					0.22126499999999999,
					323.04950981249999,
					0.98634500000000003,
					0.64096900000000001,
					0.217948,
					323.04975487500002,
					0.98733199999999999,
					0.64663300000000001,
					0.21464800000000001,
					323.05000000000001,
					0.98826000000000003,
					0.65232500000000004,
					0.211364,
					323.050245125,
					0.98912800000000001,
					0.65804300000000004,
					0.20810000000000001,
					323.05049018749997,
					0.98993500000000001,
					0.66378700000000002,
					0.20485900000000001,
					323.05073531250002,
					0.99068100000000003,
					0.66955799999999999,
					0.20164199999999999,
					323.05098037499999,
					0.99136500000000005,
					0.67535500000000004,
					0.19845299999999999,
					323.05122549999999,
					0.99198500000000001,
					0.68117899999999998,
					0.195295,
					323.05147056250001,
					0.99254100000000001,
					0.68703000000000003,
					0.19217000000000001,
					323.05171568750001,
					0.99303200000000003,
					0.69290700000000005,
					0.189084,
					323.0519608125,
					0.99345600000000001,
					0.69881000000000004,
					0.18604100000000001,
					323.05220587500003,
					0.99381399999999998,
					0.70474099999999995,
					0.18304300000000001,
					323.05245100000002,
					0.99410299999999996,
					0.71069800000000005,
					0.18009700000000001,
					323.05269606249999,
					0.99432399999999999,
					0.71668100000000001,
					0.177208,
					323.05294118749998,
					0.99447399999999997,
					0.72269099999999997,
					0.17438100000000001,
					323.05318625000001,
					0.99455300000000002,
					0.72872800000000004,
					0.171622,
					323.053431375,
					0.99456100000000003,
					0.73479099999999997,
					0.168938,
					323.05367649999999,
					0.99449500000000002,
					0.74087999999999998,
					0.16633500000000001,
					323.05392156250002,
					0.99435499999999999,
					0.74699499999999996,
					0.16382099999999999,
					323.05416668750001,
					0.99414100000000005,
					0.75313699999999995,
					0.16140399999999999,
					323.05441174999999,
					0.99385100000000004,
					0.75930399999999998,
					0.15909200000000001,
					323.05465687499998,
					0.99348199999999998,
					0.76549900000000004,
					0.156891,
					323.05490193750001,
					0.99303300000000005,
					0.77171999999999996,
					0.154808,
					323.0551470625,
					0.99250499999999997,
					0.77796699999999996,
					0.15285499999999999,
					323.05539218749999,
					0.99189700000000003,
					0.78423900000000002,
					0.15104200000000001,
					323.05563725000002,
					0.99120900000000001,
					0.79053700000000005,
					0.14937700000000001,
					323.05588237500001,
					0.99043899999999996,
					0.79685899999999998,
					0.14787,
					323.05612743749998,
					0.98958699999999999,
					0.80320499999999995,
					0.14652899999999999,
					323.05637256249997,
					0.98864799999999997,
					0.80957900000000005,
					0.14535699999999999,
					323.056617625,
					0.98762099999999997,
					0.81597799999999998,
					0.14436299999999999,
					323.05686274999999,
					0.98650899999999997,
					0.82240100000000005,
					0.14355699999999999,
					323.05710781250002,
					0.98531400000000002,
					0.82884599999999997,
					0.14294499999999999,
					323.05735293750001,
					0.98403099999999999,
					0.83531500000000003,
					0.14252799999999999,
					323.05759806250001,
					0.982653,
					0.841812,
					0.14230300000000001,
					323.05784312499998,
					0.98119000000000001,
					0.848329,
					0.14227899999999999,
					323.05808825000003,
					0.97964399999999996,
					0.85486600000000001,
					0.142453,
					323.0583333125,
					0.97799499999999995,
					0.86143199999999998,
					0.14280799999999999,
					323.05857843749999,
					0.97626500000000005,
					0.86801600000000001,
					0.14335100000000001,
					323.05882350000002,
					0.97444299999999995,
					0.87462200000000001,
					0.14406099999999999,
					323.05906862500001,
					0.97253000000000001,
					0.88124999999999998,
					0.144923,
					323.05931375,
					0.97053299999999998,
					0.88789600000000002,
					0.14591899999999999,
					323.05955881249997,
					0.96844300000000005,
					0.89456400000000003,
					0.14701400000000001,
					323.05980393750002,
					0.96627099999999999,
					0.90124899999999997,
					0.14818000000000001,
					323.06004899999999,
					0.96402100000000002,
					0.90795000000000003,
					0.14937,
					323.06029412499998,
					0.96168100000000001,
					0.91467200000000004,
					0.15051999999999999,
					323.06053918750001,
					0.95927600000000002,
					0.92140699999999998,
					0.15156600000000001,
					323.0607843125,
					0.95680799999999999,
					0.92815199999999998,
					0.15240899999999999,
					323.0610294375,
					0.954287,
					0.93490799999999996,
					0.152921,
					323.06127450000002,
					0.95172599999999996,
					0.94167100000000004,
					0.15292500000000001,
					323.06151962500002,
					0.94915099999999997,
					0.94843500000000003,
					0.15217800000000001,
					323.06176468749999,
					0.94660200000000005,
					0.95518999999999998,
					0.15032799999999999,
					323.06200981249998,
					0.94415199999999999,
					0.96191599999999999,
					0.14686099999999999,
					323.06225487500001,
					0.94189599999999996,
					0.96858999999999995,
					0.140956,
					323.0625,
					0.94001500000000004,
					0.97515799999999997,
					0.131326
				]
			}
		},
		"alphagas" : 
		{
			"PVLookupTable" : 
			{
				"RGBPoints" : 
				[
					-1.7690992540028298e-20,
					0.48004799999999997,
					0.81744099999999997,
					0.99805600000000005,
					0.062744999999999995,
					0.425898,
					0.72692100000000004,
					0.88318700000000006,
					0.12548999999999999,
					0.36668200000000001,
					0.62944500000000003,
					0.76193599999999995,
					0.1882355,
					0.30875599999999997,
					0.53100199999999997,
					0.64021700000000004,
					0.2509805,
					0.258021,
					0.43704999999999999,
					0.52343300000000004,
					0.31372549999999999,
					0.21924399999999999,
					0.352381,
					0.416348,
					0.37647049999999999,
					0.19512699999999999,
					0.281032,
					0.32297900000000002,
					0.43921549999999998,
					0.18628600000000001,
					0.22627,
					0.24652499999999999,
					0.50196078499999996,
					0.192352,
					0.19236,
					0.19236400000000001,
					0.56470600000000004,
					0.25592700000000002,
					0.21446899999999999,
					0.19175600000000001,
					0.62745099999999998,
					0.34045900000000001,
					0.25442599999999999,
					0.20666599999999999,
					0.69019600000000003,
					0.44465500000000002,
					0.30931500000000001,
					0.23402899999999999,
					0.75294100000000008,
					0.56535299999999999,
					0.376004,
					0.27096900000000002,
					0.81568649999999998,
					0.69791700000000001,
					0.45074799999999998,
					0.31429299999999999,
					0.87843150000000003,
					0.83665699999999998,
					0.52906399999999998,
					0.36022700000000002,
					0.94117650000000008,
					0.97269499999999998,
					0.61488399999999999,
					0.41312300000000002,
					1.0,
					1.0,
					0.70590399999999998,
					0.47269899999999998
				]
			}
		}
	},
	"lookup_tables" : 
	{
		"PVLookupTable" : 
		{
			"RGBPoints" : 
			[
				0.0,
				0.32549,
				0.14902000000000001,
				0.96078399999999997,
				5.9099749874195595,
				0.29704700000000001,
				0.37558599999999998,
				0.96383600000000003,
				11.819994151989402,
				0.18030199999999999,
				0.53681800000000002,
				0.96462700000000001,
				17.729969139408961,
				0.13020000000000001,
				0.64920699999999998,
				0.929647,
				23.639944126828524,
				0.0445143,
				0.74965400000000004,
				0.85599800000000004,
				29.54991911424808,
				0.0271325,
				0.83071300000000003,
				0.72152700000000003,
				35.459938278817923,
				0.25950400000000001,
				0.86614500000000005,
				0.54355500000000001,
				41.369904430807431,
				0.42836400000000002,
				0.89072499999999999,
				0.32981899999999997,
				47.279892671372075,
				0.56850299999999998,
				0.89850799999999997,
				0.18762300000000001,
				53.189863241076608,
				0.738259,
				0.89031700000000003,
				0.082546099999999997,
				59.099882405646447,
				0.84545999999999999,
				0.86136000000000001,
				0.0147555,
				65.009857393066014,
				0.91219099999999997,
				0.80801800000000001,
				0.0,
				70.919832380485559,
				0.96284800000000004,
				0.71044499999999999,
				0.0,
				76.829807367905119,
				0.99946900000000005,
				0.60025799999999996,
				0.017628399999999999,
				82.739826532474979,
				0.99415600000000004,
				0.44597500000000001,
				0.193912,
				88.354300561666037,
				0.98040700000000003,
				0.24710499999999999,
				0.26269900000000002
			]
		}
	},
	"piecewise_functions" : 
	{
		"PiecewiseFunction" : 
		{
			"Points" : 
			[
				323.0,
				0.0,
				0.5,
				0.0,
				323.0625,
				1.0,
				0.5,
				0.0
			]
		}
	},
	"representations" : 
	{
		"GeometryRepresentation" : 
		{
			"BlockColorsDistinctValues" : 12,
			"EdgeColor" : 
			[
				0.25098040699958801,
				0.25098040699958801,
				0.25098040699958801
			],
			"GaussianRadius" : 1.6988643910735845e-05,
			"GlyphTableIndexArray" : "None",
			"OSPRayScaleFunction" : 
			{
				"PiecewiseFunction" : 
				{
					"Points" : 
					[
						0.0,
						0.0,
						0.5,
						0.0,
						88.354300561666037,
						1.0,
						0.5,
						0.0
					],
					"Selected" : true
				}
			},
			"OpacityArray" : 
			[
				"",
				"",
				"",
				"",
				""
			],
			"OpacityTransferFunction" : 
			{
				"PiecewiseFunction" : 
				{
					"Points" : 
					[
						0.0,
						0.0,
						0.5,
						0.0,
						88.354300561666037,
						1.0,
						0.5,
						0.0
					],
					"Selected" : true
				}
			},
			"PolarAxes" : 
			{
				"PolarAxesRepresentation" : 
				{
					"Selected" : true
				}
			},
			"ScaleFactor" : 0.00033977287821471694,
			"ScaleTransferFunction" : 
			{
				"PiecewiseFunction" : 
				{
					"Points" : 
					[
						0.0,
						0.0,
						0.5,
						0.0,
						88.354300561666037,
						1.0,
						0.5,
						0.0
					],
					"Selected" : true
				}
			},
			"SelectInputVectors" : 
			[
				"",
				"",
				"",
				"",
				""
			],
			"SelectNormalArray" : "None",
			"SelectOrientationVectors" : "None",
			"SelectScaleArray" : "None",
			"SelectTCoordArray" : "None",
			"SelectTangentArray" : "None",
			"SetScaleArray" : 
			[
				"",
				"",
				"",
				"",
				""
			]
		},
		"UnstructuredGridRepresentation" : 
		{
			"Assembly" : "Hierarchy",
			"BlockColorsDistinctValues" : 12,
			"EdgeColor" : 
			[
				0.25098040699958801,
				0.25098040699958801,
				0.25098040699958801
			],
			"GaussianRadius" : 1.6950872377492489e-05,
			"GlyphTableIndexArray" : "None",
			"OSPRayScaleFunction" : 
			{
				"PiecewiseFunction" : 
				{
					"Points" : 
					[
						0.0,
						0.0,
						0.5,
						0.0,
						88.354300561666037,
						1.0,
						0.5,
						0.0
					],
					"Selected" : true
				}
			},
			"OpacityArray" : 
			[
				"",
				"",
				"",
				"",
				""
			],
			"OpacityArrayName" : 
			[
				"",
				"",
				"",
				"",
				""
			],
			"OpacityTransferFunction" : 
			{
				"PiecewiseFunction" : 
				{
					"Points" : 
					[
						0.0,
						0.0,
						0.5,
						0.0,
						88.354300561666037,
						1.0,
						0.5,
						0.0
					],
					"Selected" : true
				}
			},
			"PolarAxes" : 
			{
				"PolarAxesRepresentation" : 
				{
					"Selected" : true
				}
			},
			"Representation" : "Surface With Edges",
			"ScalarOpacityUnitDistance" : 0.00015951212562127933,
			"ScaleFactor" : 0.00033901744754984977,
			"ScaleTransferFunction" : 
			{
				"PiecewiseFunction" : 
				{
					"Points" : 
					[
						0.0,
						0.0,
						0.5,
						0.0,
						88.354300561666037,
						1.0,
						0.5,
						0.0
					],
					"Selected" : true
				}
			},
			"SelectInputVectors" : 
			[
				"",
				"",
				"",
				"",
				""
			],
			"SelectNormalArray" : "None",
			"SelectOrientationVectors" : "None",
			"SelectScaleArray" : "None",
			"SelectTCoordArray" : "None",
			"SelectTangentArray" : "None",
			"SetScaleArray" : 
			[
				"",
				"",
				"",
				"",
				""
			]
		}
	},
	"settings" : 
	{
		"ColorPalette" : 
		{
			"BackgroundColor" : 
			[
				0.32000000000000001,
				0.34000000000000002,
				0.42999999999999999
			]
		}
	},
	"sources" : 
	{
		"PVFoamReader" : 
		{
			"FieldStatus" : 
			[
				"T",
				"0",
				"T.gas",
				"0",
				"T.liquid",
				"0",
				"alpha.gas",
				"0",
				"epsilon",
				"0",
				"k",
				"0",
				"nut",
				"0",
				"omega",
				"0",
				"p",
				"0",
				"p_rgh",
				"0",
				"U",
				"0"
			],
			"FileName" : "/scratch/project_462000770/stashes1/compressibleVoF/sprayCBreakUpRAS.sttmp/sprayCBreakUpRAS.sttmp.OpenFOAM",
			"PartStatus" : 
			[
				"inlet - patch",
				"0",
				"internalMesh",
				"1",
				"level1 - cellZone",
				"1",
				"level2 - cellZone",
				"1",
				"outlet - wall",
				"0",
				"tip - wall",
				"0",
				"wall - group",
				"0"
			],
			"UiShowPatchNames" : 1,
			"UiUseVTKPolyhedron" : 1
		}
	}
}
